gitterest/__init__.py
gitterest-0.1.dist-info/DESCRIPTION.rst
gitterest-0.1.dist-info/METADATA
gitterest-0.1.dist-info/RECORD
gitterest-0.1.dist-info/WHEEL
gitterest-0.1.dist-info/metadata.json
gitterest-0.1.dist-info/top_level.txt
