Metadata-Version: 2.0
Name: gitterest
Version: 0.1
Summary: A simple gitter API wrapper inspired by gitterpy.
Home-page: https://gitlab.com/coala/gitterest
Author: Alex Hiam, Lasse Schuirmann
Author-email: lasse.schuirmann@gmail.com
License: UNKNOWN
Platform: UNKNOWN
